README.txt
setup.py
docs/HISTORY.txt
z3c/__init__.py
z3c.metrics.egg-info/PKG-INFO
z3c.metrics.egg-info/SOURCES.txt
z3c.metrics.egg-info/dependency_links.txt
z3c.metrics.egg-info/entry_points.txt
z3c.metrics.egg-info/namespace_packages.txt
z3c.metrics.egg-info/not-zip-safe
z3c.metrics.egg-info/requires.txt
z3c.metrics.egg-info/top_level.txt
z3c/metrics/README.txt
z3c/metrics/__init__.py
z3c/metrics/bbb.py
z3c/metrics/configure.zcml
z3c/metrics/container.zcml
z3c/metrics/dispatch.py
z3c/metrics/dispatch.txt
z3c/metrics/dispatch.zcml
z3c/metrics/engine.py
z3c/metrics/event.txt
z3c/metrics/index.py
z3c/metrics/index.txt
z3c/metrics/interfaces.py
z3c/metrics/meta.py
z3c/metrics/meta.txt
z3c/metrics/meta.zcml
z3c/metrics/metric.py
z3c/metrics/scale.py
z3c/metrics/scale.txt
z3c/metrics/subscription.py
z3c/metrics/testing.py
z3c/metrics/testing.zcml
z3c/metrics/tests.py
z3c/metrics/verify.txt
z3c/metrics/zope2/__init__.py
z3c/metrics/zope2/at.zcml
z3c/metrics/zope2/catalog.txt
z3c/metrics/zope2/configure.zcml
z3c/metrics/zope2/container.zcml
z3c/metrics/zope2/creator.py
z3c/metrics/zope2/discussion.py
z3c/metrics/zope2/discussion.zcml
z3c/metrics/zope2/dispatch.zcml
z3c/metrics/zope2/index.py
z3c/metrics/zope2/index.zcml
z3c/metrics/zope2/meta.py
z3c/metrics/zope2/meta.zcml
z3c/metrics/zope2/ofs.py
z3c/metrics/zope2/scale.py
z3c/metrics/zope2/teamspace.py
z3c/metrics/zope2/testing.py
z3c/metrics/zope2/testing.zcml
z3c/metrics/zope2/tests.py