Metadata-Version: 1.0
Name: z3c.metrics
Version: 0.1
Summary: Index arbitrary values as scores for object metrics.
Home-page: http://pypi.python.org/pypi/z3c.metrics
Author: Ross Patterson
Author-email: me@rpatterson.net
License: ZPL
Keywords: zope zop3 index
Platform: UNKNOWN
Classifier: Programming Language :: Python
Classifier: Topic :: Software Development :: Libraries :: Python Modules
